src/__init__.py
src/disk_usage.py
FDASST-0.2.dist-info/LICENSE
FDASST-0.2.dist-info/METADATA
FDASST-0.2.dist-info/WHEEL
FDASST-0.2.dist-info/top_level.txt
FDASST-0.2.dist-info/RECORD
