Metadata-Version: 2.1
Name: FDASST
Version: 0.2
Summary: A Python package to read disk usage also known as File Disk And System Stats Tool
Home-page: https://github.com/CoderLogy/Python-Disk-Usage
Author: Shourya Wadhwa
Author-email: sourceboxtv@gmail.com
License: GPL-3.0-or-later
Classifier: Programming Language :: Python :: 3
Classifier: License :: OSI Approved :: GNU General Public License v3 (GPLv3)
Classifier: Operating System :: OS Independent
Requires-Python: >=3.8
License-File: LICENSE
Requires-Dist: psutil
Requires-Dist: resource
